{
    "mail": {
        "username": "zx...",
        "password": "supersecret",
        "smtpserv": "smtpserv.uni-tuebingen.de",
        "fromaddress": "hhi@fsi.uni-tuebingen.de",
        "fromname": "FSI HHI",
        "replyToAddress": "fsi@fsi.uni-tuebingen.de",
        "replyToName": "FSI"
    },
    "shiftFile": "./shifts.json",
    "baseUrl": "http://localhost:8080/index.php",
    "hashSalt": "muchmoresecret",
    "enableRegister": true,
    "enableUnregister": true,
    "hideNames": false,
    "hidePdfExport": false
}
